rosecape_utils/__init__.py
rosecape_utils/secrets/__init__.py
rosecape_utils/secrets/secrets.py
rosecape_utils/tests/__init__.py
rosecape_utils/tests/pytest.ini
rosecape_utils/tests/test_secrets.py
rosecape_utils-0.2.2.dist-info/METADATA
rosecape_utils-0.2.2.dist-info/WHEEL
rosecape_utils-0.2.2.dist-info/RECORD
