Metadata-Version: 2.1
Name: rosecape_utils
Version: 0.2.2
Summary: 
Author: VincentVinet
Author-email: vincent@rosecape.ca
Requires-Python: >=3.8
Classifier: Programming Language :: Python :: 3
Classifier: Programming Language :: Python :: 3.8
Classifier: Programming Language :: Python :: 3.9
Classifier: Programming Language :: Python :: 3.10
Classifier: Programming Language :: Python :: 3.11
Classifier: Programming Language :: Python :: 3.12
Requires-Dist: azure-identity (>=1.16.1,<2.0.0)
Requires-Dist: azure-keyvault-secrets (>=4.8.0,<5.0.0)
Requires-Dist: boto3 (>=1.34.126,<2.0.0)
